[
    {
        "id": 13333,
        "title_romaji": "TARI TARI",
        "title_english": "Tari Tari",
        "title_native": "TARI TARI",
        "format": "TV",
        "episodes": 13,
        "duration": 24,
        "source": "ORIGINAL",
        "country": "JP",
        "isAdult": false,
        "score": 72,
        "meanScore": 72,
        "popularity": 37755,
        "favourites": 856,
        "trending": 0,
        "genres": "Music, Slice of Life",
        "tags": "Ensemble Cast, Coastal, Coming of Age, School Club, Band, School, Animals, Family Life, Tragedy, Cute Girls Doing Cute Things, Female Protagonist",
        "status": "FINISHED",
        "studio": "P.A.WORKS",
        "season": "SUMMER",
        "start_year": 2012,
        "url": "https://anilist.co/anime/13333"
    },
    {
        "id": 138060,
        "title_romaji": "Star Wars: Visions",
        "title_english": "Star Wars: Visions",
        "title_native": "スター・ウォーズ：ビジョンズ",
        "format": "ONA",
        "episodes": 9,
        "duration": 16,
        "source": "ORIGINAL",
        "country": "JP",
        "isAdult": false,
        "score": 71,
        "meanScore": 71,
        "popularity": 37698,
        "favourites": 412,
        "trending": 0,
        "genres": "Action, Adventure, Sci-Fi",
        "tags": "Space, Anthology, Swordplay, Space Opera, Aliens, Episodic, Artificial Intelligence, Robots, Tragedy, Fugitive, Cultivation, Military, Anti-Hero, Samurai, Archery, Ensemble Cast, Terrorism, Twins, Anthropomorphism, CGI, Adoption, Band, Parenthood, Marriage, Achromatic, Musical Theater",
        "status": "FINISHED",
        "studio": "Kinema Citrus",
        "season": "FALL",
        "start_year": 2021,
        "url": "https://anilist.co/anime/138060"
    },
    {
        "id": 164172,
        "title_romaji": "Amagami-san Chi no Enmusubi",
        "title_english": "Tying the Knot with an Amagami Sister",
        "title_native": "甘神さんちの縁結び",
        "format": "TV",
        "episodes": 24,
        "duration": 24,
        "source": "MANGA",
        "country": "JP",
        "isAdult": false,
        "score": 73,
        "meanScore": 73,
        "popularity": 37618,
        "favourites": 858,
        "trending": 3,
        "genres": "Comedy, Drama, Ecchi, Romance, Supernatural",
        "tags": "Heterosexual, Shrine Maiden, Female Harem, Primarily Female Cast, Male Protagonist, Coming of Age, Family Life, Tsundere, Found Family, Slapstick, Urban Fantasy, Memory Manipulation, Shounen, Body Swapping, Time Loop, Adoption, Religion, Time Manipulation, Cute Girls Doing Cute Things, Alternate Universe, Age Gap, Nudity, Tomboy, Isekai, Chibi, Yandere, School, Ojou-sama",
        "status": "FINISHED",
        "studio": "Drive",
        "season": "FALL",
        "start_year": 2024,
        "url": "https://anilist.co/anime/164172"
    },
    {
        "id": 160447,
        "title_romaji": "Temple",
        "title_english": "TenPuru",
        "title_native": "てんぷる",
        "format": "TV",
        "episodes": 12,
        "duration": 24,
        "source": "MANGA",
        "country": "JP",
        "isAdult": false,
        "score": 65,
        "meanScore": 65,
        "popularity": 37614,
        "favourites": 702,
        "trending": 0,
        "genres": "Comedy, Drama, Ecchi, Romance, Slice of Life",
        "tags": "Heterosexual, Female Harem, Large Breasts, Male Protagonist, Nudity, Slapstick, Tsundere, Primarily Female Cast, Surreal Comedy, Religion, Seinen, Philosophy, Archery, Arranged Marriage",
        "status": "FINISHED",
        "studio": "Gekkou",
        "season": "SUMMER",
        "start_year": 2023,
        "url": "https://anilist.co/anime/160447"
    },
    {
        "id": 20656,
        "title_romaji": "Gugure! Kokkuri-san",
        "title_english": "Gugure! Kokkuri-san",
        "title_native": "繰繰れ!コックリさん",
        "format": "TV",
        "episodes": 12,
        "duration": 24,
        "source": "MANGA",
        "country": "JP",
        "isAdult": false,
        "score": 72,
        "meanScore": 72,
        "popularity": 37588,
        "favourites": 481,
        "trending": 0,
        "genres": "Comedy, Supernatural",
        "tags": "Episodic, Chibi, Youkai, Meta, Female Protagonist, Kemonomimi, Shounen, Male Protagonist, Ghost, Nekomimi, Gender Bending, Ensemble Cast, Amnesia, Iyashikei, Aliens, Guns, Tsundere, Kuudere, Age Regression, Crossdressing",
        "status": "FINISHED",
        "studio": "TMS Entertainment",
        "season": "FALL",
        "start_year": 2014,
        "url": "https://anilist.co/anime/20656"
    },
    {
        "id": 14753,
        "title_romaji": "Hori-san to Miyamura-kun",
        "title_english": null,
        "title_native": "堀さんと宮村くん",
        "format": "OVA",
        "episodes": 6,
        "duration": 23,
        "source": "MANGA",
        "country": "JP",
        "isAdult": false,
        "score": 72,
        "meanScore": 72,
        "popularity": 37584,
        "favourites": 467,
        "trending": 0,
        "genres": "Comedy, Romance, Slice of Life",
        "tags": "School, Female Protagonist, Male Protagonist, Heterosexual, Primarily Teen Cast, Family Life, Slapstick, Tsundere, Shounen",
        "status": "FINISHED",
        "studio": "Hoods Entertainment",
        "season": "SUMMER",
        "start_year": 2012,
        "url": "https://anilist.co/anime/14753"
    },
    {
        "id": 6954,
        "title_romaji": "Kara no Kyoukai: Shuushou",
        "title_english": "the Garden of sinners Chapter 8: The Final Chapter",
        "title_native": "空の境界 終章",
        "format": "OVA",
        "episodes": 1,
        "duration": 33,
        "source": "OTHER",
        "country": "JP",
        "isAdult": false,
        "score": 71,
        "meanScore": 71,
        "popularity": 37517,
        "favourites": 578,
        "trending": 0,
        "genres": "Mystery, Psychological, Supernatural",
        "tags": "Dissociative Identities, Philosophy, Urban Fantasy, Primarily Adult Cast, Female Protagonist, Urban, Male Protagonist, Snowscape",
        "status": "FINISHED",
        "studio": "ufotable",
        "season": "WINTER",
        "start_year": 2011,
        "url": "https://anilist.co/anime/6954"
    },
    {
        "id": 174802,
        "title_romaji": "Shiunji-ke no Kodomotachi",
        "title_english": "The Shiunji Family Children",
        "title_native": "紫雲寺家の子供たち",
        "format": "TV",
        "episodes": 12,
        "duration": 24,
        "source": "MANGA",
        "country": "JP",
        "isAdult": false,
        "score": 70,
        "meanScore": 70,
        "popularity": 37492,
        "favourites": 909,
        "trending": 4,
        "genres": "Comedy, Romance",
        "tags": "Inseki, Female Harem, Heterosexual, Primarily Female Cast, Adoption, Male Protagonist, Seinen, Coming of Age, Tsundere, Kuudere, Slapstick, Nudity, CGI, Tennis, Mountaineering, School",
        "status": "FINISHED",
        "studio": "Doga Kobo",
        "season": "SPRING",
        "start_year": 2025,
        "url": "https://anilist.co/anime/174802"
    },
    {
        "id": 154966,
        "title_romaji": "Fate/strange Fake: Whispers of Dawn",
        "title_english": "Fate/strange Fake -Whispers of Dawn-",
        "title_native": "Fate/strange Fake -Whispers of Dawn-",
        "format": "SPECIAL",
        "episodes": 1,
        "duration": 55,
        "source": "LIGHT_NOVEL",
        "country": "JP",
        "isAdult": false,
        "score": 81,
        "meanScore": 81,
        "popularity": 37482,
        "favourites": 701,
        "trending": 1,
        "genres": "Action, Adventure, Fantasy, Mystery, Supernatural",
        "tags": "Magic, Mythology, Foreign, Gods, Shapeshifting, Agender, Chimera, Conspiracy, Battle Royale, Urban Fantasy, Animals, Death Game, Vampire, Swordplay, Police, Urban, Guns, Assassins, Isekai",
        "status": "FINISHED",
        "studio": "A-1 Pictures",
        "season": "SUMMER",
        "start_year": 2023,
        "url": "https://anilist.co/anime/154966"
    },
    {
        "id": 16035,
        "title_romaji": "Karneval (TV)",
        "title_english": "Karneval (TV)",
        "title_native": "カーニヴァル (TV)",
        "format": "TV",
        "episodes": 13,
        "duration": 24,
        "source": "MANGA",
        "country": "JP",
        "isAdult": false,
        "score": 66,
        "meanScore": 66,
        "popularity": 37463,
        "favourites": 396,
        "trending": 0,
        "genres": "Action, Fantasy, Mystery, Sci-Fi",
        "tags": "Amnesia, Circus, Josei, Male Protagonist, Primarily Male Cast, Magic, Guns, Kemonomimi",
        "status": "FINISHED",
        "studio": "Manglobe",
        "season": "SPRING",
        "start_year": 2013,
        "url": "https://anilist.co/anime/16035"
    },
    {
        "id": 905,
        "title_romaji": "Dragon Ball Z: Fukkatsu no Fusion!! Goku to Vegeta",
        "title_english": "Dragon Ball Z: Fusion Reborn",
        "title_native": "ドラゴンボールＺ 復活のフュージョン!!悟空とベジータ",
        "format": "MOVIE",
        "episodes": 1,
        "duration": 55,
        "source": "MANGA",
        "country": "JP",
        "isAdult": false,
        "score": 73,
        "meanScore": 74,
        "popularity": 37434,
        "favourites": 503,
        "trending": 0,
        "genres": "Action, Adventure, Sci-Fi",
        "tags": "Shounen, Super Power, Demons, Male Protagonist, Martial Arts, Henshin, Aliens, Afterlife",
        "status": "FINISHED",
        "studio": "Toei Animation",
        "season": "SPRING",
        "start_year": 1995,
        "url": "https://anilist.co/anime/905"
    },
    {
        "id": 6747,
        "title_romaji": "Dance in the Vampire Bund",
        "title_english": "Dance in the Vampire Bund",
        "title_native": "ダンスインザヴァンパイアバンド",
        "format": "TV",
        "episodes": 12,
        "duration": 24,
        "source": "MANGA",
        "country": "JP",
        "isAdult": false,
        "score": 65,
        "meanScore": 65,
        "popularity": 37407,
        "favourites": 303,
        "trending": 0,
        "genres": "Action, Ecchi, Romance, Supernatural",
        "tags": "Vampire, Amnesia, Urban Fantasy, Werewolf, Heterosexual, Cohabitation, Nudity, Urban, Seinen, Age Gap, Clone, Politics, School, Love Triangle, Body Horror, Maids, Female Harem, Nun",
        "status": "FINISHED",
        "studio": "Shaft",
        "season": "WINTER",
        "start_year": 2010,
        "url": "https://anilist.co/anime/6747"
    },
    {
        "id": 135102,
        "title_romaji": "Kamitachi ni Hirowareta Otoko 2",
        "title_english": "By the Grace of the Gods 2",
        "title_native": "神達に拾われた男２",
        "format": "TV",
        "episodes": 12,
        "duration": 24,
        "source": "LIGHT_NOVEL",
        "country": "JP",
        "isAdult": false,
        "score": 68,
        "meanScore": 68,
        "popularity": 37403,
        "favourites": 778,
        "trending": 0,
        "genres": "Adventure, Fantasy, Slice of Life",
        "tags": "Isekai, Reincarnation, Magic, Work, Gods, Demons, Iyashikei",
        "status": "FINISHED",
        "studio": "Maho Film",
        "season": "WINTER",
        "start_year": 2023,
        "url": "https://anilist.co/anime/135102"
    },
    {
        "id": 128034,
        "title_romaji": "ORIENT",
        "title_english": "ORIENT",
        "title_native": "オリエント",
        "format": "TV",
        "episodes": 12,
        "duration": 24,
        "source": "MANGA",
        "country": "JP",
        "isAdult": false,
        "score": 62,
        "meanScore": 62,
        "popularity": 37395,
        "favourites": 455,
        "trending": 2,
        "genres": "Action, Adventure, Comedy, Fantasy",
        "tags": "Kaiju, Samurai, Shounen, Swordplay, Historical, Magic, Male Protagonist, Demons, Slavery, Survival, Ninja, Gore, Gods, Nudity, Agriculture, Slapstick",
        "status": "FINISHED",
        "studio": "A.C.G.T.",
        "season": "WINTER",
        "start_year": 2022,
        "url": "https://anilist.co/anime/128034"
    },
    {
        "id": 2144,
        "title_romaji": "NARUTO: Dai Koufun! Mikazukijima no Animal Panic Dattebayo!",
        "title_english": "Naruto the Movie: Guardians of the Crescent Moon Kingdom",
        "title_native": "劇場版 NARUTO -ナルト- 大興奮!みかづき島のアニマル騒動だってばよ",
        "format": "MOVIE",
        "episodes": 1,
        "duration": 94,
        "source": "MANGA",
        "country": "JP",
        "isAdult": false,
        "score": 66,
        "meanScore": 66,
        "popularity": 37384,
        "favourites": 215,
        "trending": 0,
        "genres": "Action, Adventure",
        "tags": "Ninja, Male Protagonist, Primarily Male Cast, Circus, Animals, Primarily Child Cast, Shounen, Super Power, Archery, Kuudere, Orphan, Anachronism",
        "status": "FINISHED",
        "studio": "Studio Pierrot",
        "season": "SUMMER",
        "start_year": 2006,
        "url": "https://anilist.co/anime/2144"
    },
    {
        "id": 168872,
        "title_romaji": "Kimi ni Todoke 3RD SEASON",
        "title_english": "Kimi ni Todoke: From Me to You Season 3",
        "title_native": "君に届け 3RD SEASON",
        "format": "ONA",
        "episodes": 5,
        "duration": 67,
        "source": "MANGA",
        "country": "JP",
        "isAdult": false,
        "score": 84,
        "meanScore": 84,
        "popularity": 37374,
        "favourites": 982,
        "trending": 1,
        "genres": "Comedy, Drama, Romance, Slice of Life",
        "tags": "Shoujo, Coming of Age, Female Protagonist, Heterosexual, School, Primarily Teen Cast, Tomboy, Tsundere, Male Protagonist, Chibi, Snowscape, Unrequited Love, Teacher, Gyaru, Tragedy",
        "status": "FINISHED",
        "studio": "Production I.G",
        "season": "SUMMER",
        "start_year": 2024,
        "url": "https://anilist.co/anime/168872"
    },
    {
        "id": 2889,
        "title_romaji": "BLEACH: The DiamondDust Rebellion - Mou Hitotsu no Hyourinmaru",
        "title_english": "Bleach the Movie: The DiamondDust Rebellion",
        "title_native": "BLEACH The DiamondDust Rebellion もう一つの氷輪丸",
        "format": "MOVIE",
        "episodes": 1,
        "duration": 92,
        "source": "ORIGINAL",
        "country": "JP",
        "isAdult": false,
        "score": 70,
        "meanScore": 70,
        "popularity": 37367,
        "favourites": 288,
        "trending": 0,
        "genres": "Action, Adventure, Drama, Supernatural",
        "tags": "Shounen, Afterlife, Male Protagonist, Super Power, Swordplay, Kuudere, School, Urban Fantasy",
        "status": "FINISHED",
        "studio": "Studio Pierrot",
        "season": "FALL",
        "start_year": 2007,
        "url": "https://anilist.co/anime/2889"
    },
    {
        "id": 240,
        "title_romaji": "Genshiken",
        "title_english": "Genshiken",
        "title_native": "げんしけん",
        "format": "TV",
        "episodes": 12,
        "duration": 25,
        "source": "MANGA",
        "country": "JP",
        "isAdult": false,
        "score": 74,
        "meanScore": 74,
        "popularity": 37326,
        "favourites": 514,
        "trending": 0,
        "genres": "Comedy, Slice of Life",
        "tags": "Otaku Culture, School Club, Parody, Cosplay, College, Meta, Ensemble Cast, Primarily Adult Cast, Seinen, Heterosexual, Male Protagonist, Video Games",
        "status": "FINISHED",
        "studio": "Palm Studio",
        "season": "FALL",
        "start_year": 2004,
        "url": "https://anilist.co/anime/240"
    },
    {
        "id": 119056,
        "title_romaji": "Kenja no Deshi wo Nanoru Kenja",
        "title_english": "She Professed Herself Pupil of the Wise Man",
        "title_native": "賢者の弟子を名乗る賢者",
        "format": "TV",
        "episodes": 12,
        "duration": 24,
        "source": "LIGHT_NOVEL",
        "country": "JP",
        "isAdult": false,
        "score": 59,
        "meanScore": 59,
        "popularity": 37324,
        "favourites": 503,
        "trending": 0,
        "genres": "Adventure, Fantasy",
        "tags": "Isekai, Female Protagonist, Magic, Virtual World, Gender Bending, CGI, Dungeon",
        "status": "FINISHED",
        "studio": "studio A-CAT",
        "season": "WINTER",
        "start_year": 2022,
        "url": "https://anilist.co/anime/119056"
    },
    {
        "id": 154692,
        "title_romaji": "Kanojo mo Kanojo Season 2",
        "title_english": "Girlfriend, Girlfriend Season 2",
        "title_native": "カノジョも彼女 Season 2",
        "format": "TV",
        "episodes": 12,
        "duration": 24,
        "source": "MANGA",
        "country": "JP",
        "isAdult": false,
        "score": 69,
        "meanScore": 69,
        "popularity": 37300,
        "favourites": 632,
        "trending": 0,
        "genres": "Comedy, Ecchi, Romance, Slice of Life",
        "tags": "Female Harem, Heterosexual, Love Triangle, Male Protagonist, Slapstick, Primarily Female Cast, Polyamorous, Parody, Primarily Teen Cast, School, Shounen, Nudity, Disability, Bisexual, Yuri",
        "status": "FINISHED",
        "studio": "SynergySP",
        "season": "FALL",
        "start_year": 2023,
        "url": "https://anilist.co/anime/154692"
    },
    {
        "id": 9734,
        "title_romaji": "K-ON!!: Keikaku!",
        "title_english": "K-ON! Season 2: Plan!",
        "title_native": "けいおん!! 計画!",
        "format": "OVA",
        "episodes": 1,
        "duration": 23,
        "source": "MANGA",
        "country": "JP",
        "isAdult": false,
        "score": 77,
        "meanScore": 77,
        "popularity": 37287,
        "favourites": 290,
        "trending": 0,
        "genres": "Comedy, Music, Slice of Life",
        "tags": "Cute Girls Doing Cute Things, Band, School, Primarily Female Cast, Female Protagonist, Seinen, Iyashikei, Primarily Teen Cast, Ensemble Cast, Tsundere, Rock Music, Tomboy",
        "status": "FINISHED",
        "studio": "Kyoto Animation",
        "season": "SPRING",
        "start_year": 2011,
        "url": "https://anilist.co/anime/9734"
    },
    {
        "id": 161802,
        "title_romaji": "Tensei Shitara Slime Datta Ken: Coleus no Yume",
        "title_english": "That Time I Got Reincarnated as a Slime: Visions of Coleus",
        "title_native": "転生したらスライムだった件 コリウスの夢",
        "format": "OVA",
        "episodes": 3,
        "duration": 24,
        "source": "OTHER",
        "country": "JP",
        "isAdult": false,
        "score": 76,
        "meanScore": 76,
        "popularity": 37252,
        "favourites": 685,
        "trending": 2,
        "genres": "Action, Adventure, Comedy, Fantasy",
        "tags": "Royal Affairs, Isekai, Magic, Politics, Vampire, Demons, Shapeshifting, Monster Boy, Agender, Super Power, Youkai, Male Protagonist, Economics, Medieval",
        "status": "FINISHED",
        "studio": "8-bit",
        "season": "FALL",
        "start_year": 2023,
        "url": "https://anilist.co/anime/161802"
    },
    {
        "id": 142701,
        "title_romaji": "Koukyuu no Karasu",
        "title_english": "Raven of the Inner Palace",
        "title_native": "後宮の烏",
        "format": "TV",
        "episodes": 13,
        "duration": 24,
        "source": "LIGHT_NOVEL",
        "country": "JP",
        "isAdult": false,
        "score": 73,
        "meanScore": 73,
        "popularity": 37238,
        "favourites": 772,
        "trending": 2,
        "genres": "Drama, Fantasy, Mystery, Supernatural",
        "tags": "Female Protagonist, Foreign, Historical, Primarily Adult Cast, Detective, Kuudere, Mythology, Magic, Episodic, Necromancy, Shoujo, Conspiracy, Politics, Ghost, Suicide, Tsundere, Heterosexual, Maids, Ojou-sama, Body Horror, Orphan, Ancient China, Rape",
        "status": "FINISHED",
        "studio": "Bandai Namco Pictures",
        "season": "FALL",
        "start_year": 2022,
        "url": "https://anilist.co/anime/142701"
    },
    {
        "id": 21563,
        "title_romaji": "Clockwork Planet",
        "title_english": "Clockwork Planet",
        "title_native": "クロックワーク・プラネット",
        "format": "TV",
        "episodes": 12,
        "duration": 25,
        "source": "LIGHT_NOVEL",
        "country": "JP",
        "isAdult": false,
        "score": 58,
        "meanScore": 58,
        "popularity": 37144,
        "favourites": 345,
        "trending": 1,
        "genres": "Drama, Ecchi, Fantasy, Romance, Sci-Fi",
        "tags": "Robots, Steampunk, Artificial Intelligence, Male Protagonist, Ensemble Cast, Post-Apocalyptic, Dystopian, Female Harem, Super Power, Terrorism, Anti-Hero, Female Protagonist, Male Harem, Cyborg, Crossdressing, Educational, Nudity",
        "status": "FINISHED",
        "studio": "Xebec",
        "season": "SPRING",
        "start_year": 2017,
        "url": "https://anilist.co/anime/21563"
    },
    {
        "id": 97669,
        "title_romaji": "orange: Mirai",
        "title_english": "Orange: Future",
        "title_native": "orange -未来-",
        "format": "MOVIE",
        "episodes": 1,
        "duration": 65,
        "source": "MANGA",
        "country": "JP",
        "isAdult": false,
        "score": 73,
        "meanScore": 73,
        "popularity": 37134,
        "favourites": 297,
        "trending": 1,
        "genres": "Drama, Psychological, Romance, Sci-Fi, Supernatural",
        "tags": "Shoujo, School, Male Protagonist, Love Triangle, Alternate Universe, Heterosexual, Time Manipulation",
        "status": "FINISHED",
        "studio": "Telecom Animation Film",
        "season": "FALL",
        "start_year": 2016,
        "url": "https://anilist.co/anime/97669"
    },
    {
        "id": 17777,
        "title_romaji": "Saikin, Imouto no Yousu ga Chotto Okashiinda ga.",
        "title_english": "Recently, My Sister Is Unusual",
        "title_native": "最近、妹のようすがちょっとおかしいんだが。",
        "format": "TV",
        "episodes": 12,
        "duration": 23,
        "source": "MANGA",
        "country": "JP",
        "isAdult": false,
        "score": 57,
        "meanScore": 57,
        "popularity": 37114,
        "favourites": 213,
        "trending": 1,
        "genres": "Comedy, Ecchi, Romance, Supernatural",
        "tags": "Dissociative Identities, Shounen, Inseki, Ghost, Female Protagonist, Tragedy, LGBTQ+ Themes, Disability, Kuudere, Bisexual",
        "status": "FINISHED",
        "studio": "project No.9",
        "season": "WINTER",
        "start_year": 2014,
        "url": "https://anilist.co/anime/17777"
    },
    {
        "id": 21138,
        "title_romaji": "Akatsuki no Yona OVA",
        "title_english": "Yona of the Dawn OVA",
        "title_native": "暁のヨナ OVA",
        "format": "OVA",
        "episodes": 3,
        "duration": 23,
        "source": "MANGA",
        "country": "JP",
        "isAdult": false,
        "score": 79,
        "meanScore": 80,
        "popularity": 37080,
        "favourites": 541,
        "trending": 0,
        "genres": "Action, Comedy, Fantasy, Romance",
        "tags": "Shoujo, Primarily Male Cast, Female Protagonist, Archery, Historical, Dragons, Tragedy, Mythology, Male Harem, Gods, Heterosexual, Politics",
        "status": "FINISHED",
        "studio": "Studio Pierrot",
        "season": "FALL",
        "start_year": 2015,
        "url": "https://anilist.co/anime/21138"
    },
    {
        "id": 901,
        "title_romaji": "Dragon Ball Z: Moetsukiro!! Nessen - Ressen - Chou Gekisen",
        "title_english": "Dragon Ball Z: Broly - The Legendary Super Saiyan",
        "title_native": "ドラゴンボールZ 燃えつきろ!!熱戦・烈戦・超激戦",
        "format": "MOVIE",
        "episodes": 1,
        "duration": 72,
        "source": "MANGA",
        "country": "JP",
        "isAdult": false,
        "score": 70,
        "meanScore": 70,
        "popularity": 37054,
        "favourites": 400,
        "trending": 0,
        "genres": "Action, Adventure, Sci-Fi",
        "tags": "Shounen, Super Power, Martial Arts, Aliens, Male Protagonist, Henshin",
        "status": "FINISHED",
        "studio": "Toei Animation",
        "season": "WINTER",
        "start_year": 1993,
        "url": "https://anilist.co/anime/901"
    },
    {
        "id": 99390,
        "title_romaji": "Miira no Kaikata",
        "title_english": "How to Keep a Mummy",
        "title_native": "ミイラの飼い方",
        "format": "TV",
        "episodes": 12,
        "duration": 24,
        "source": "MANGA",
        "country": "JP",
        "isAdult": false,
        "score": 72,
        "meanScore": 72,
        "popularity": 37038,
        "favourites": 603,
        "trending": 0,
        "genres": "Comedy, Slice of Life, Supernatural",
        "tags": "Iyashikei, Male Protagonist, School, Youkai, Animals, Cute Boys Doing Cute Things, Dragons, Ensemble Cast",
        "status": "FINISHED",
        "studio": "8-bit",
        "season": "WINTER",
        "start_year": 2018,
        "url": "https://anilist.co/anime/99390"
    },
    {
        "id": 1829,
        "title_romaji": "Ged Senki",
        "title_english": "Tales from Earthsea",
        "title_native": "ゲド戦記",
        "format": "MOVIE",
        "episodes": 1,
        "duration": 115,
        "source": "OTHER",
        "country": "JP",
        "isAdult": false,
        "score": 64,
        "meanScore": 64,
        "popularity": 36982,
        "favourites": 369,
        "trending": 0,
        "genres": "Adventure, Fantasy",
        "tags": "Magic, Medieval, Male Protagonist, Dragons, Dissociative Identities, Orphan, Slavery, Swordplay, Travel, Agriculture, Drugs, Ships",
        "status": "FINISHED",
        "studio": "Studio Ghibli",
        "season": "SUMMER",
        "start_year": 2006,
        "url": "https://anilist.co/anime/1829"
    },
    {
        "id": 5060,
        "title_romaji": "Hetalia Axis Powers",
        "title_english": "Hetalia Axis Powers",
        "title_native": "ヘタリア Axis Powers",
        "format": "ONA",
        "episodes": 52,
        "duration": 5,
        "source": "MANGA",
        "country": "JP",
        "isAdult": false,
        "score": 65,
        "meanScore": 65,
        "popularity": 36950,
        "favourites": 403,
        "trending": 0,
        "genres": "Comedy",
        "tags": "Parody, Historical, Slapstick, Primarily Male Cast, Educational, Cute Boys Doing Cute Things, Male Protagonist, Politics, Anthropomorphism, Anachronism, Chibi, Maids, Economics, Astronomy",
        "status": "FINISHED",
        "studio": "Studio DEEN",
        "season": "WINTER",
        "start_year": 2009,
        "url": "https://anilist.co/anime/5060"
    },
    {
        "id": 21712,
        "title_romaji": "ISLAND",
        "title_english": "ISLAND",
        "title_native": "ISLAND",
        "format": "TV",
        "episodes": 12,
        "duration": 24,
        "source": "VISUAL_NOVEL",
        "country": "JP",
        "isAdult": false,
        "score": 57,
        "meanScore": 58,
        "popularity": 36949,
        "favourites": 320,
        "trending": 1,
        "genres": "Drama, Mystery, Romance, Sci-Fi",
        "tags": "Time Skip, Amnesia, Tragedy, Time Manipulation, Heterosexual, Coastal, Love Triangle, Female Harem, Shrine Maiden, Male Protagonist, Tsundere",
        "status": "FINISHED",
        "studio": "feel.",
        "season": "SUMMER",
        "start_year": 2018,
        "url": "https://anilist.co/anime/21712"
    },
    {
        "id": 107672,
        "title_romaji": "Katsute Kami Datta Kemono-tachi e",
        "title_english": "To the Abandoned Sacred Beasts",
        "title_native": "かつて神だった獣たちへ",
        "format": "TV",
        "episodes": 12,
        "duration": 24,
        "source": "MANGA",
        "country": "JP",
        "isAdult": false,
        "score": 61,
        "meanScore": 61,
        "popularity": 36906,
        "favourites": 351,
        "trending": 0,
        "genres": "Action, Drama, Fantasy, Mystery, Supernatural",
        "tags": "Military, Tragedy, Gore, Henshin, War, Werewolf, Kaiju, Shounen, Historical, Guns, Vampire, Foreign, Dragons, Mythology, Zombie",
        "status": "FINISHED",
        "studio": "MAPPA",
        "season": "SUMMER",
        "start_year": 2019,
        "url": "https://anilist.co/anime/107672"
    },
    {
        "id": 97643,
        "title_romaji": "Berserk 2",
        "title_english": "Berserk 2",
        "title_native": "ベルセルク 2",
        "format": "TV",
        "episodes": 12,
        "duration": 24,
        "source": "MANGA",
        "country": "JP",
        "isAdult": false,
        "score": 60,
        "meanScore": 60,
        "popularity": 36845,
        "favourites": 411,
        "trending": 0,
        "genres": "Action, Adventure, Drama, Fantasy, Horror, Supernatural",
        "tags": "CGI, Seinen, Full CGI, Magic, Elf, Demons, Revenge, Swordplay, Medieval, Male Protagonist, Witch, Gods, Medicine, Gore, Tragedy, Rape, Ghost, Military, Disability, Skeleton",
        "status": "FINISHED",
        "studio": "Millepensee",
        "season": "SPRING",
        "start_year": 2017,
        "url": "https://anilist.co/anime/97643"
    },
    {
        "id": 100085,
        "title_romaji": "Shichisei no Subaru",
        "title_english": "Seven Senses of the Re'Union",
        "title_native": "七星のスバル",
        "format": "TV",
        "episodes": 12,
        "duration": 24,
        "source": "LIGHT_NOVEL",
        "country": "JP",
        "isAdult": false,
        "score": 56,
        "meanScore": 56,
        "popularity": 36824,
        "favourites": 327,
        "trending": 0,
        "genres": "Action, Drama, Fantasy, Romance, Sci-Fi",
        "tags": "Video Games, Virtual World, Primarily Female Cast, Isekai, Love Triangle, Time Skip, Male Protagonist, CGI, Magic, Time Manipulation",
        "status": "FINISHED",
        "studio": "Lerche",
        "season": "SUMMER",
        "start_year": 2018,
        "url": "https://anilist.co/anime/100085"
    },
    {
        "id": 97983,
        "title_romaji": "Natsume Yuujinchou Roku",
        "title_english": "Natsume's Book of Friends Season 6",
        "title_native": "夏目友人帳 陸",
        "format": "TV",
        "episodes": 11,
        "duration": 24,
        "source": "MANGA",
        "country": "JP",
        "isAdult": false,
        "score": 85,
        "meanScore": 85,
        "popularity": 36796,
        "favourites": 675,
        "trending": 1,
        "genres": "Drama, Fantasy, Slice of Life, Supernatural",
        "tags": "Youkai, Iyashikei, Male Protagonist, Shoujo, Episodic, Adoption, Rural, Primarily Teen Cast, Shapeshifting, Urban Fantasy, Estranged Family, School, Age Regression, Exorcism, Amnesia",
        "status": "FINISHED",
        "studio": "Shuka",
        "season": "SPRING",
        "start_year": 2017,
        "url": "https://anilist.co/anime/97983"
    },
    {
        "id": 4835,
        "title_romaji": "BLEACH: Fade to Black - Kimi no Na wo Yobu",
        "title_english": "Bleach the Movie: Fade to Black",
        "title_native": "BLEACH Fade to Black 君の名を呼ぶ",
        "format": "MOVIE",
        "episodes": 1,
        "duration": 94,
        "source": "ORIGINAL",
        "country": "JP",
        "isAdult": false,
        "score": 71,
        "meanScore": 71,
        "popularity": 36791,
        "favourites": 297,
        "trending": 1,
        "genres": "Action, Adventure, Drama, Supernatural",
        "tags": "Shounen, Super Power, Swordplay, Male Protagonist, Afterlife, Memory Manipulation, Female Protagonist, Amnesia, Kuudere",
        "status": "FINISHED",
        "studio": "Studio Pierrot",
        "season": "FALL",
        "start_year": 2008,
        "url": "https://anilist.co/anime/4835"
    },
    {
        "id": 15059,
        "title_romaji": "Initial D Fifth Stage",
        "title_english": null,
        "title_native": "頭文字〈イニシャル〉D Fifth Stage",
        "format": "TV",
        "episodes": 14,
        "duration": 27,
        "source": "MANGA",
        "country": "JP",
        "isAdult": false,
        "score": 79,
        "meanScore": 79,
        "popularity": 36780,
        "favourites": 651,
        "trending": 0,
        "genres": "Action, Drama, Sports",
        "tags": "Cars, Rural, CGI, Male Protagonist, Primarily Male Cast, Seinen, Heterosexual, Primarily Adult Cast, Love Triangle",
        "status": "FINISHED",
        "studio": "SynergySP",
        "season": "FALL",
        "start_year": 2012,
        "url": "https://anilist.co/anime/15059"
    },
    {
        "id": 3167,
        "title_romaji": "Eve no Jikan: Are you enjoying the time of EVE?",
        "title_english": "Time of Eve",
        "title_native": "イヴの時間 Are you enjoying the time of EVE ?",
        "format": "ONA",
        "episodes": 6,
        "duration": 19,
        "source": "ORIGINAL",
        "country": "JP",
        "isAdult": false,
        "score": 77,
        "meanScore": 77,
        "popularity": 36758,
        "favourites": 382,
        "trending": 0,
        "genres": "Sci-Fi, Slice of Life",
        "tags": "Robots, Artificial Intelligence, Philosophy, Bar, Male Protagonist, Urban, Amnesia, Surreal Comedy, CGI, Found Family, Female Protagonist",
        "status": "FINISHED",
        "studio": "Studio Rikka",
        "season": "SUMMER",
        "start_year": 2008,
        "url": "https://anilist.co/anime/3167"
    },
    {
        "id": 101249,
        "title_romaji": "Penguin Highway",
        "title_english": "Penguin Highway",
        "title_native": "ペンギン・ハイウェイ",
        "format": "MOVIE",
        "episodes": 1,
        "duration": 118,
        "source": "OTHER",
        "country": "JP",
        "isAdult": false,
        "score": 74,
        "meanScore": 74,
        "popularity": 36710,
        "favourites": 506,
        "trending": 0,
        "genres": "Drama, Mystery, Sci-Fi, Slice of Life",
        "tags": "Coming of Age, Animals, Urban Fantasy, Male Protagonist, Philosophy, Kids, Primarily Child Cast, Environmental, School, Rural, CGI, Bullying, Swimming, Female Protagonist",
        "status": "FINISHED",
        "studio": "Studio Colorido",
        "season": "SUMMER",
        "start_year": 2018,
        "url": "https://anilist.co/anime/101249"
    },
    {
        "id": 21710,
        "title_romaji": "Natsume Yuujinchou Go",
        "title_english": "Natsume's Book of Friends Season 5",
        "title_native": "夏目友人帳 伍",
        "format": "TV",
        "episodes": 11,
        "duration": 24,
        "source": "MANGA",
        "country": "JP",
        "isAdult": false,
        "score": 84,
        "meanScore": 84,
        "popularity": 36656,
        "favourites": 688,
        "trending": 1,
        "genres": "Drama, Fantasy, Slice of Life, Supernatural",
        "tags": "Iyashikei, Youkai, Male Protagonist, Episodic, Adoption, Shoujo, Rural, Primarily Teen Cast, Urban Fantasy, Shapeshifting, Exorcism, Outdoor Activities, School, Estranged Family",
        "status": "FINISHED",
        "studio": "Shuka",
        "season": "FALL",
        "start_year": 2016,
        "url": "https://anilist.co/anime/21710"
    },
    {
        "id": 146234,
        "title_romaji": "Isekai One Turn Kill Nee-san: Ane Douhan no Isekai Seikatsu Hajimemashita",
        "title_english": "My One-Hit Kill Sister",
        "title_native": "異世界ワンターンキル姉さん ～姉同伴の異世界生活はじめました～",
        "format": "TV",
        "episodes": 12,
        "duration": 24,
        "source": "OTHER",
        "country": "JP",
        "isAdult": false,
        "score": 60,
        "meanScore": 60,
        "popularity": 36639,
        "favourites": 588,
        "trending": 0,
        "genres": "Comedy, Fantasy, Romance",
        "tags": "Isekai, Incest, Heterosexual, Primarily Female Cast, Male Protagonist, Female Protagonist, Magic, Parody, Demons, Swordplay, Goblin, Maids, Ojou-sama, Nudity, Crossover, Female Harem, Angels, Shogi",
        "status": "FINISHED",
        "studio": "Gekkou",
        "season": "SPRING",
        "start_year": 2023,
        "url": "https://anilist.co/anime/146234"
    },
    {
        "id": 4548,
        "title_romaji": "Yozakura Quartet",
        "title_english": null,
        "title_native": "夜桜四重奏 ～ヨザクラカルテット～",
        "format": "TV",
        "episodes": 12,
        "duration": 24,
        "source": "MANGA",
        "country": "JP",
        "isAdult": false,
        "score": 65,
        "meanScore": 65,
        "popularity": 36633,
        "favourites": 199,
        "trending": 0,
        "genres": "Action, Comedy, Supernatural",
        "tags": "Shounen, Magic, Guns, Female Protagonist, Youkai, Nekomimi, Kemonomimi, Urban Fantasy, Super Power, Demons, Swordplay",
        "status": "FINISHED",
        "studio": "Nomad",
        "season": "FALL",
        "start_year": 2008,
        "url": "https://anilist.co/anime/4548"
    },
    {
        "id": 165254,
        "title_romaji": "BUCCHIGIRI?!",
        "title_english": "BUCCHIGIRI?!",
        "title_native": "ぶっちぎり?!",
        "format": "TV",
        "episodes": 12,
        "duration": 24,
        "source": "ORIGINAL",
        "country": "JP",
        "isAdult": false,
        "score": 64,
        "meanScore": 64,
        "popularity": 36608,
        "favourites": 605,
        "trending": 1,
        "genres": "Action, Supernatural",
        "tags": "Martial Arts, Delinquents, Gangs, Primarily Teen Cast, School, Primarily Male Cast, Mythology, Magic, Male Protagonist, Unrequited Love, Heterosexual, Boys' Love, Revenge, LGBTQ+ Themes, Cute Boys Doing Cute Things, Tragedy",
        "status": "FINISHED",
        "studio": "MAPPA",
        "season": "WINTER",
        "start_year": 2024,
        "url": "https://anilist.co/anime/165254"
    },
    {
        "id": 3702,
        "title_romaji": "Detroit Metal City",
        "title_english": null,
        "title_native": "デトロイト・メタル・シティ",
        "format": "OVA",
        "episodes": 12,
        "duration": 13,
        "source": "MANGA",
        "country": "JP",
        "isAdult": false,
        "score": 76,
        "meanScore": 76,
        "popularity": 36602,
        "favourites": 694,
        "trending": 0,
        "genres": "Comedy, Music",
        "tags": "Band, Surreal Comedy, Parody, Metal Music, College, Urban, Male Protagonist, Primarily Adult Cast, Seinen, Rape, Gender Bending, Rural, Drugs",
        "status": "FINISHED",
        "studio": "Studio 4°C",
        "season": "SUMMER",
        "start_year": 2008,
        "url": "https://anilist.co/anime/3702"
    },
    {
        "id": 21318,
        "title_romaji": "Fate/stay night: Unlimited Blade Works 2nd Season - sunny day",
        "title_english": "Fate/stay night: Unlimited Blade Works 2nd Season - sunny day",
        "title_native": "Fate/stay night [Unlimited Blade Works] 2ndシーズン - sunny day",
        "format": "SPECIAL",
        "episodes": 1,
        "duration": 10,
        "source": "VISUAL_NOVEL",
        "country": "JP",
        "isAdult": false,
        "score": 72,
        "meanScore": 73,
        "popularity": 36592,
        "favourites": 275,
        "trending": 0,
        "genres": "Action, Fantasy",
        "tags": "Magic, Alternate Universe, Bisexual, Love Triangle, Gender Bending, Battle Royale, Polyamorous, Kuudere",
        "status": "FINISHED",
        "studio": "ufotable",
        "season": "FALL",
        "start_year": 2015,
        "url": "https://anilist.co/anime/21318"
    },
    {
        "id": 1571,
        "title_romaji": "Ghost Hunt",
        "title_english": "Ghost Hunt",
        "title_native": "ゴーストハント",
        "format": "TV",
        "episodes": 25,
        "duration": 25,
        "source": "LIGHT_NOVEL",
        "country": "JP",
        "isAdult": false,
        "score": 73,
        "meanScore": 73,
        "popularity": 36552,
        "favourites": 599,
        "trending": 0,
        "genres": "Comedy, Horror, Mystery, Supernatural",
        "tags": "Ghost, Detective, Denpa, Youkai, Tragedy, Shrine Maiden, Female Protagonist, Super Power, Shoujo, Disability, Exorcism, Gods, Demons, Body Horror, Gore, Curses, Cars, Ensemble Cast, Crime",
        "status": "FINISHED",
        "studio": "J.C.STAFF",
        "season": "FALL",
        "start_year": 2006,
        "url": "https://anilist.co/anime/1571"
    },
    {
        "id": 21356,
        "title_romaji": "Pocket Monsters XY&Z",
        "title_english": "Pokémon the Series: XYZ",
        "title_native": "ポケットモンスター XY&Z",
        "format": "TV",
        "episodes": 47,
        "duration": 24,
        "source": "VIDEO_GAME",
        "country": "JP",
        "isAdult": false,
        "score": 77,
        "meanScore": 77,
        "popularity": 36451,
        "favourites": 975,
        "trending": 0,
        "genres": "Action, Adventure, Comedy, Fantasy",
        "tags": "Animals, Primarily Child Cast, Male Protagonist, War, Magic, Proxy Battle, Kids, Female Protagonist, Slapstick, Henshin, Super Robot, Love Triangle, Heterosexual, Creature Taming",
        "status": "FINISHED",
        "studio": "OLM",
        "season": "FALL",
        "start_year": 2015,
        "url": "https://anilist.co/anime/21356"
    },
    {
        "id": 178434,
        "title_romaji": "Tensei Kizoku, Kantei Skill de Nariagaru 2nd Season",
        "title_english": "As a Reincarnated Aristocrat, I'll Use My Appraisal Skill to Rise in the World Season 2",
        "title_native": "転生貴族、鑑定スキルで成り上がる 第2期",
        "format": "TV",
        "episodes": 12,
        "duration": 24,
        "source": "LIGHT_NOVEL",
        "country": "JP",
        "isAdult": false,
        "score": 74,
        "meanScore": 74,
        "popularity": 36435,
        "favourites": 681,
        "trending": 1,
        "genres": "Adventure, Fantasy",
        "tags": "Military, Politics, Coming of Age, Isekai, War, Royal Affairs, Male Protagonist, Heterosexual, Reincarnation, Marriage, Magic, Swordplay, Crossdressing, Anti-Hero",
        "status": "FINISHED",
        "studio": "studio MOTHER",
        "season": "FALL",
        "start_year": 2024,
        "url": "https://anilist.co/anime/178434"
    },
    {
        "id": 12883,
        "title_romaji": "Tsuritama",
        "title_english": "Tsuritama",
        "title_native": "つり球",
        "format": "TV",
        "episodes": 12,
        "duration": 23,
        "source": "ORIGINAL",
        "country": "JP",
        "isAdult": false,
        "score": 73,
        "meanScore": 73,
        "popularity": 36398,
        "favourites": 699,
        "trending": 0,
        "genres": "Comedy, Sci-Fi, Slice of Life, Sports",
        "tags": "Fishing, Coming of Age, Aliens, Male Protagonist, Cute Boys Doing Cute Things, Tanned Skin, Primarily Teen Cast, Family Life, Coastal, Shapeshifting, Memory Manipulation, Primarily Male Cast, Fugitive, Outdoor Activities, Dancing, School",
        "status": "FINISHED",
        "studio": "A-1 Pictures",
        "season": "SPRING",
        "start_year": 2012,
        "url": "https://anilist.co/anime/12883"
    }
]