[
  {
    "id": 275332787,
    "title": "Sách Cuộc Thập Tự Chinh Thứ Nhất",
    "price": 231288,
    "discount": 41,
    "rating": 4.6,
    "reviews": 17,
    "quantity_sold": 216,
    "original_price": 389000,
    "category_l1": "Nhà Sách Tiki",
    "category_l2": "Sách tiếng Việt",
    "category_l3": "Sách Lịch sử",
    "category_l4": "",
    "primary_category": "Lịch Sử Thế Giới",
    "url": "https://tiki.vn/sach-cuoc-thap-tu-chinh-thu-nhat-p275332787.html?spid=275332789"
  },
  {
    "id": 274599269,
    "title": "Sách Nơi Nào Có Mẹ, Nơi Ấy Là Nhà",
    "price": 65000,
    "discount": 28,
    "rating": 5.0,
    "reviews": 12,
    "quantity_sold": 397,
    "original_price": 90000,
    "category_l1": "Nhà Sách Tiki",
    "category_l2": "Sách tiếng Việt",
    "category_l3": "Sách văn học",
    "category_l4": "",
    "primary_category": "Truyện ngắn - Tản văn - Tạp Văn",
    "url": "https://tiki.vn/sach-noi-nao-co-me-noi-ay-la-nha-p274599269.html?spid=274599608"
  },
  {
    "id": 273822788,
    "title": "Sách Ngày mai, ngày mai và ngày mai nữa",
    "price": 189000,
    "discount": 27,
    "rating": 5.0,
    "reviews": 58,
    "quantity_sold": 649,
    "original_price": 259000,
    "category_l1": "Nhà Sách Tiki",
    "category_l2": "Sách tiếng Việt",
    "category_l3": "Sách văn học",
    "category_l4": "",
    "primary_category": "Truyện dài",
    "url": "https://tiki.vn/sach-ngay-mai-ngay-mai-va-ngay-mai-nua-p273822788.html?spid=273822789"
  },
  {
    "id": 273457566,
    "title": "Sách Thép đã tôi thế đấy (Bản dịch đầy đủ nhất) - Bìa mềm",
    "price": 86000,
    "discount": 31,
    "rating": 4.7,
    "reviews": 125,
    "quantity_sold": 844,
    "original_price": 125000,
    "category_l1": "Nhà Sách Tiki",
    "category_l2": "Sách tiếng Việt",
    "category_l3": "Sách văn học",
    "category_l4": "Tác phẩm kinh điển",
    "primary_category": "Tác Phẩm Kinh Điển Nước Ngoài",
    "url": "https://tiki.vn/sach-thep-da-toi-the-day-ban-dich-day-du-nhat-bia-mem-p273457566.html?spid=273457569"
  },
  {
    "id": 273219043,
    "title": "Sách Tuổi 20 - Những Năm Tháng Quyết Định Cuộc Đời Bạn",
    "price": 70500,
    "discount": 35,
    "rating": 4.7,
    "reviews": 117,
    "quantity_sold": 507,
    "original_price": 109000,
    "category_l1": "Nhà Sách Tiki",
    "category_l2": "Sách tiếng Việt",
    "category_l3": "Sách kỹ năng sống",
    "category_l4": "",
    "primary_category": "Sách tư duy - Kỹ năng sống",
    "url": "https://tiki.vn/sach-tuoi-20-nhung-nam-thang-quyet-dinh-cuoc-doi-ban-p273219043.html?spid=273219046"
  },
  {
    "id": 271199015,
    "title": "Sách Thân Ai Nấy Lo – Sự thật về tình yêu, tình thân và bản chất con người",
    "price": 123750,
    "discount": 25,
    "rating": 5.0,
    "reviews": 15,
    "quantity_sold": 311,
    "original_price": 165000,
    "category_l1": "Nhà Sách Tiki",
    "category_l2": "Sách tiếng Việt",
    "category_l3": "Sách kỹ năng sống",
    "category_l4": "",
    "primary_category": "Sách tư duy - Kỹ năng sống",
    "url": "https://tiki.vn/sach-than-ai-nay-lo-su-that-ve-tinh-yeu-tinh-than-va-ban-chat-con-nguoi-p271199015.html?spid=271199016"
  },
  {
    "id": 269946656,
    "title": "Giải Mã Hoóc-Môn Dopamin",
    "price": 142400,
    "discount": 28,
    "rating": 5.0,
    "reviews": 8,
    "quantity_sold": 129,
    "original_price": 198000,
    "category_l1": "Nhà Sách Tiki",
    "category_l2": "Sách tiếng Việt",
    "category_l3": "Sách kỹ năng sống",
    "category_l4": "",
    "primary_category": "Sách tư duy - Kỹ năng sống",
    "url": "https://tiki.vn/giai-ma-hooc-mon-dopamin-p269946656.html?spid=269946657"
  },
  {
    "id": 241821098,
    "title": "Thả Một Bè Lau - Truyện Kiều Dưới Cái Nhìn Thiền Quán",
    "price": 133000,
    "discount": 26,
    "rating": 5.0,
    "reviews": 44,
    "quantity_sold": 486,
    "original_price": 179000,
    "category_l1": "Nhà Sách Tiki",
    "category_l2": "Sách tiếng Việt",
    "category_l3": "Sách Tôn Giáo - Tâm Linh",
    "category_l4": "",
    "primary_category": "Phật giáo",
    "url": "https://tiki.vn/tha-mot-be-lau-truyen-kieu-duoi-cai-nhin-thien-quan-p241821098.html?spid=241821100"
  },
  {
    "id": 241758784,
    "title": "Sách Đánh Giá Kết Quả Đào Tạo",
    "price": 168300,
    "discount": 34,
    "rating": 5.0,
    "reviews": 10,
    "quantity_sold": 177,
    "original_price": 255000,
    "category_l1": "Nhà Sách Tiki",
    "category_l2": "Sách tiếng Việt",
    "category_l3": "Sách kinh tế",
    "category_l4": "",
    "primary_category": "Sách kỹ năng làm việc",
    "url": "https://tiki.vn/sach-danh-gia-ket-qua-dao-tao-p241758784.html?spid=241758786"
  },
  {
    "id": 111285050,
    "title": "Sách Ai Lấy Miếng Pho Mát Của Tôi ? (Tái Bản)",
    "price": 47600,
    "discount": 30,
    "rating": 5.0,
    "reviews": 111,
    "quantity_sold": 2081,
    "original_price": 68000,
    "category_l1": "Nhà Sách Tiki",
    "category_l2": "Sách tiếng Việt",
    "category_l3": "Sách kỹ năng sống",
    "category_l4": "Sách kỹ năng mềm",
    "primary_category": "Nghệ thuật sống",
    "url": "https://tiki.vn/sach-ai-lay-mieng-pho-mat-cua-toi-tai-ban-p111285050.html?spid=111285051"
  },
  {
    "id": 77112144,
    "title": "Sách Keep It Up Tập Viết Chữ Hán - Học Tiếng Trung Cho Người Mới Bắt Đầu",
    "price": 43400,
    "discount": 26,
    "rating": 4.8,
    "reviews": 171,
    "quantity_sold": 1002,
    "original_price": 59000,
    "category_l1": "Nhà Sách Tiki",
    "category_l2": "Sách tiếng Việt",
    "category_l3": "Sách Học Ngoại Ngữ",
    "category_l4": "Sách Học Tiếng Hoa",
    "primary_category": "Tập viết chữ Hán",
    "url": "https://tiki.vn/sach-keep-it-up-tap-viet-chu-han-hoc-tieng-trung-cho-nguoi-moi-bat-dau-p77112144.html?spid=77112146"
  },
  {
    "id": 76014598,
    "title": "Sách Blue Ocean Strategy - Chiến Lược Đại Dương Xanh (Bìa Cứng) (Tái Bản)",
    "price": 148180,
    "discount": 38,
    "rating": 5.0,
    "reviews": 301,
    "quantity_sold": 2821,
    "original_price": 239000,
    "category_l1": "Nhà Sách Tiki",
    "category_l2": "Sách tiếng Việt",
    "category_l3": "Sách kinh tế",
    "category_l4": "",
    "primary_category": "Sách quản trị, lãnh đạo",
    "url": "https://tiki.vn/sach-blue-ocean-strategy-chien-luoc-dai-duong-xanh-bia-cung-tai-ban-p76014598.html?spid=76014599"
  },
  {
    "id": 76013378,
    "title": "Sách Storytelling With Data - Kể Chuyện Thông Qua Dữ Liệu (Cuốn Cẩm Nang Hướng Dẫn Trực Quan Hóa Dữ Liệu)",
    "price": 187827,
    "discount": 41,
    "rating": 5.0,
    "reviews": 1931,
    "quantity_sold": 12613,
    "original_price": 319000,
    "category_l1": "Nhà Sách Tiki",
    "category_l2": "Sách tiếng Việt",
    "category_l3": "Sách kinh tế",
    "category_l4": "",
    "primary_category": "Sách kỹ năng làm việc",
    "url": "https://tiki.vn/sach-storytelling-with-data-ke-chuyen-thong-qua-du-lieu-cuon-cam-nang-huong-dan-truc-quan-hoa-du-lieu-p76013378.html?spid=76013379"
  },
  {
    "id": 73120237,
    "title": "Sách Đừng Coi Thường Sự Lười Học Của Con Người",
    "price": 39000,
    "discount": 71,
    "rating": 4.7,
    "reviews": 45,
    "quantity_sold": 538,
    "original_price": 135000,
    "category_l1": "Nhà Sách Tiki",
    "category_l2": "Sách tiếng Việt",
    "category_l3": "Sách kỹ năng sống",
    "category_l4": "Sách kỹ năng mềm",
    "primary_category": "Kỹ Năng Khác",
    "url": "https://tiki.vn/sach-dung-coi-thuong-su-luoi-hoc-cua-con-nguoi-p73120237.html?spid=73120238"
  },
  {
    "id": 58390336,
    "title": "Python cơ bản",
    "price": 125000,
    "discount": 0,
    "rating": 4.8,
    "reviews": 909,
    "quantity_sold": 4461,
    "original_price": 125000,
    "category_l1": "Nhà Sách Tiki",
    "category_l2": "Sách tiếng Việt",
    "category_l3": "Sách Công Nghệ Thông Tin",
    "category_l4": "",
    "primary_category": "Lập Trình",
    "url": "https://tiki.vn/python-co-ban-p58390336.html?spid=58390337"
  },
  {
    "id": 53434797,
    "title": "Sách Tài Chính Cá Nhân Cho Người Việt Nam - Tặng Khóa học Online về Tài chính",
    "price": 122000,
    "discount": 39,
    "rating": 4.8,
    "reviews": 1807,
    "quantity_sold": 13682,
    "original_price": 200000,
    "category_l1": "Nhà Sách Tiki",
    "category_l2": "Sách tiếng Việt",
    "category_l3": "Sách kinh tế",
    "category_l4": "Sách tài chính",
    "primary_category": "Tài chính cá nhân",
    "url": "https://tiki.vn/sach-tai-chinh-ca-nhan-cho-nguoi-viet-nam-tang-khoa-hoc-online-ve-tai-chinh-p53434797.html?spid=53434798"
  },
  {
    "id": 19588948,
    "title": "Sách Tâm Lý Dân Tộc An Nam",
    "price": 70500,
    "discount": 35,
    "rating": 4.5,
    "reviews": 209,
    "quantity_sold": 4098,
    "original_price": 109000,
    "category_l1": "Nhà Sách Tiki",
    "category_l2": "Sách tiếng Việt",
    "category_l3": "Sách Lịch sử",
    "category_l4": "",
    "primary_category": "Lịch Sử Việt Nam",
    "url": "https://tiki.vn/sach-tam-ly-dan-toc-an-nam-p19588948.html?spid=19588949"
  },
  {
    "id": 10379317,
    "title": "Sách Nghệ Thuật Giao Tiếp Để Thành Công (Tái Bản 2019)",
    "price": 108971,
    "discount": 36,
    "rating": 4.8,
    "reviews": 600,
    "quantity_sold": 5895,
    "original_price": 169000,
    "category_l1": "Nhà Sách Tiki",
    "category_l2": "Sách tiếng Việt",
    "category_l3": "Sách kỹ năng sống",
    "category_l4": "",
    "primary_category": "Sách tư duy - Kỹ năng sống",
    "url": "https://tiki.vn/sach-nghe-thuat-giao-tiep-de-thanh-cong-tai-ban-2019-p10379317.html?spid=10379318"
  },
  {
    "id": 377644,
    "title": "Sách Chờ Đến Mẫu Giáo Thì Đã Muộn",
    "price": 48990,
    "discount": 29,
    "rating": 4.7,
    "reviews": 715,
    "quantity_sold": 38069,
    "original_price": 69000,
    "category_l1": "Nhà Sách Tiki",
    "category_l2": "Sách tiếng Việt",
    "category_l3": "Nuôi dạy con",
    "category_l4": "",
    "primary_category": "Cẩm nang làm cha mẹ",
    "url": "https://tiki.vn/sach-cho-den-mau-giao-thi-da-muon-p377644.html?spid=76206"
  },
  {
    "id": 347334,
    "title": "Sách Có Hai Con Mèo Ngồi Bên Cửa Sổ",
    "price": 74000,
    "discount": 26,
    "rating": 4.7,
    "reviews": 1338,
    "quantity_sold": 24469,
    "original_price": 100000,
    "category_l1": "Nhà Sách Tiki",
    "category_l2": "Sách tiếng Việt",
    "category_l3": "Sách văn học",
    "category_l4": "Tiểu Thuyết",
    "primary_category": "Tiểu Thuyết Phương Đông",
    "url": "https://tiki.vn/sach-co-hai-con-meo-ngoi-ben-cua-so-p347334.html?spid=39001"
  }
]