[
  {
    "id": 278110371,
    "title": "Chuyện nghề phán xử- những dòng chảy của ký ức",
    "price": 232800,
    "discount": 17,
    "rating": 0.0,
    "reviews": 0,
    "quantity_sold": 6,
    "original_price": 280000,
    "category_l1": "Nhà Sách Tiki",
    "category_l2": "Sách tiếng Việt",
    "category_l3": "Sách Chính Trị - Pháp Lý",
    "category_l4": "Luật - Văn Bản Luật",
    "primary_category": "Luật Dân sự",
    "url": "https://tiki.vn/chuyen-nghe-phan-xu-nhung-dong-chay-cua-ky-uc-p278110371.html?spid=278110372"
  },
  {
    "id": 277923345,
    "title": "Sách Triết Lý Sống Của Người Nhật",
    "price": 93000,
    "discount": 33,
    "rating": 0.0,
    "reviews": 0,
    "quantity_sold": 8,
    "original_price": 138000,
    "category_l1": "Nhà Sách Tiki",
    "category_l2": "Sách tiếng Việt",
    "category_l3": "Sách kỹ năng sống",
    "category_l4": "",
    "primary_category": "Sách tư duy - Kỹ năng sống",
    "url": "https://tiki.vn/sach-triet-ly-song-cua-nguoi-nhat-p277923345.html?spid=277923347"
  },
  {
    "id": 277779977,
    "title": "Trọn bộ 2 cuốn \"Ngắn 2025\" và \"Màu nhạt nắng\"",
    "price": 239000,
    "discount": 20,
    "rating": 0.0,
    "reviews": 0,
    "quantity_sold": 17,
    "original_price": 298000,
    "category_l1": "Nhà Sách Tiki",
    "category_l2": "Sách tiếng Việt",
    "category_l3": "Sách văn học",
    "category_l4": "Truyện ngắn - Tản văn - Tạp Văn",
    "primary_category": "Truyện ngắn - Tản văn - Tạp Văn Việt Nam",
    "url": "https://tiki.vn/tron-bo-2-cuon-ngan-2025-va-mau-nhat-nang-p277779977.html?spid=277779978"
  },
  {
    "id": 277408901,
    "title": "Sách Nhân Sinh Tự Tại Một Kiếp Bình An",
    "price": 101250,
    "discount": 25,
    "rating": 5.0,
    "reviews": 4,
    "quantity_sold": 56,
    "original_price": 135000,
    "category_l1": "Nhà Sách Tiki",
    "category_l2": "Sách tiếng Việt",
    "category_l3": "Sách kỹ năng sống",
    "category_l4": "",
    "primary_category": "Sách tư duy - Kỹ năng sống",
    "url": "https://tiki.vn/sach-nhan-sinh-tu-tai-mot-kiep-binh-an-p277408901.html?spid=277408904"
  },
  {
    "id": 277369421,
    "title": "Sách - Thống Kê Trong Kinh Tế Và Kinh Doanh - Statistics For Business And Economics (Tái Bản 2024)",
    "price": 341044,
    "discount": 27,
    "rating": 5.0,
    "reviews": 3,
    "quantity_sold": 27,
    "original_price": 470000,
    "category_l1": "Nhà Sách Tiki",
    "category_l2": "Sách tiếng Việt",
    "category_l3": "Sách văn học",
    "category_l4": "Tiểu Thuyết",
    "primary_category": "Tiểu Thuyết Phương Tây",
    "url": "https://tiki.vn/sach-thong-ke-trong-kinh-te-va-kinh-doanh-statistics-for-business-and-economics-tai-ban-2024-p277369421.html?spid=277369422"
  },
  {
    "id": 277338846,
    "title": "Sách Bài Tập Khoa Học Tự Nhiên 8- Cánh Diều (Kèm Nilon bọc Sách)",
    "price": 43000,
    "discount": 0,
    "rating": 4.5,
    "reviews": 2,
    "quantity_sold": 37,
    "original_price": 43000,
    "category_l1": "Nhà Sách Tiki",
    "category_l2": "Sách tiếng Việt",
    "category_l3": "Sách Giáo Khoa - Giáo Trình",
    "category_l4": "",
    "primary_category": "Sách Giáo Khoa Cấp 2",
    "url": "https://tiki.vn/sach-bai-tap-khoa-hoc-tu-nhien-8-canh-dieu-p277338846.html?spid=277338847"
  },
  {
    "id": 277164021,
    "title": "Sách Chuyện nhà Tí (và chuyện nhiều nhà khác)",
    "price": 117000,
    "discount": 22,
    "rating": 5.0,
    "reviews": 3,
    "quantity_sold": 96,
    "original_price": 150000,
    "category_l1": "Nhà Sách Tiki",
    "category_l2": "Sách tiếng Việt",
    "category_l3": "Sách văn học",
    "category_l4": "Truyện ngắn - Tản văn - Tạp Văn",
    "primary_category": "Truyện ngắn - Tản văn - Tạp Văn Việt Nam",
    "url": "https://tiki.vn/sach-chuyen-nha-ti-va-chuyen-nhieu-nha-khac-p277164021.html?spid=277164022"
  },
  {
    "id": 276526159,
    "title": "Sách Alice Ở Xứ Sở Diệu Kỳ Và Alice Ở Thế Giới Trong Gương",
    "price": 69000,
    "discount": 36,
    "rating": 4.7,
    "reviews": 3,
    "quantity_sold": 13,
    "original_price": 108000,
    "category_l1": "Nhà Sách Tiki",
    "category_l2": "Sách tiếng Việt",
    "category_l3": "Sách thiếu nhi ",
    "category_l4": "",
    "primary_category": "Truyện cổ tích",
    "url": "https://tiki.vn/sach-alice-o-xu-so-dieu-ky-va-alice-o-the-gioi-trong-guong-p276526159.html?spid=276526162"
  },
  {
    "id": 275600564,
    "title": "Sách giáo khoa Toán 9- Tập hai- Chân Trời Sáng Tạo (Kèm Nilon bọc Sách)",
    "price": 28000,
    "discount": 0,
    "rating": 5.0,
    "reviews": 1,
    "quantity_sold": 53,
    "original_price": 28000,
    "category_l1": "Nhà Sách Tiki",
    "category_l2": "Sách tiếng Việt",
    "category_l3": "Sách Giáo Khoa - Giáo Trình",
    "category_l4": "",
    "primary_category": "Sách Giáo Khoa Cấp 2",
    "url": "https://tiki.vn/sach-giao-khoa-toan-9-tap-hai-chan-troi-sang-tao-p275600564.html?spid=275600565"
  },
  {
    "id": 275506281,
    "title": "Thiên Sứ Nhà Bên (Truyện Tranh) – Tập 3",
    "price": 47500,
    "discount": 5,
    "rating": 5.0,
    "reviews": 2,
    "quantity_sold": 46,
    "original_price": 50000,
    "category_l1": "Nhà Sách Tiki",
    "category_l2": "Sách tiếng Việt",
    "category_l3": "",
    "category_l4": "",
    "primary_category": "Truyện Tranh, Manga, Comic",
    "url": "https://tiki.vn/thien-su-nha-ben-truyen-tranh-tap-3-tang-bookmark-be-hinh-postcard-in-nhu-2-mat-p275506281.html?spid=275506284"
  },
  {
    "id": 275001052,
    "title": "Sách Giáo Khoa Toán 11 - Tập 2 (Kết Nối) (Chuẩn)",
    "price": 16000,
    "discount": 0,
    "rating": 5.0,
    "reviews": 1,
    "quantity_sold": 20,
    "original_price": 16000,
    "category_l1": "Nhà Sách Tiki",
    "category_l2": "Sách tiếng Việt",
    "category_l3": "Sách Giáo Khoa - Giáo Trình",
    "category_l4": "",
    "primary_category": "Sách Giáo Khoa Cấp 3",
    "url": "https://tiki.vn/toan-11-tap-2-ket-noi-chuan-p275001052.html?spid=275001053"
  },
  {
    "id": 274826815,
    "title": "Gia Đình Gãi Ngứa - Tuyển Tập Chúng Ta Rồi Sẽ Lớn",
    "price": 108000,
    "discount": 22,
    "rating": 5.0,
    "reviews": 18,
    "quantity_sold": 160,
    "original_price": 138000,
    "category_l1": "Nhà Sách Tiki",
    "category_l2": "Sách tiếng Việt",
    "category_l3": "",
    "category_l4": "",
    "primary_category": "Truyện Tranh, Manga, Comic",
    "url": "https://tiki.vn/gia-dinh-gai-ngua-tuyen-tap-chung-ta-roi-se-lon-p274826815.html?spid=274829506"
  },
  {
    "id": 274442083,
    "title": "Sách Tạo Thói Quen Nhỏ Dựng Cuộc Đời Lớn",
    "price": 98000,
    "discount": 38,
    "rating": 5.0,
    "reviews": 7,
    "quantity_sold": 29,
    "original_price": 158000,
    "category_l1": "Nhà Sách Tiki",
    "category_l2": "Sách tiếng Việt",
    "category_l3": "Sách kỹ năng sống",
    "category_l4": "",
    "primary_category": "Sách tư duy - Kỹ năng sống",
    "url": "https://tiki.vn/sach-tao-thoi-quen-nho-dung-cuoc-doi-lon-p274442083.html?spid=274442086"
  },
  {
    "id": 274393403,
    "title": "Sách - Toán thực tế lớp 11",
    "price": 66300,
    "discount": 15,
    "rating": 4.5,
    "reviews": 2,
    "quantity_sold": 8,
    "original_price": 78000,
    "category_l1": "Nhà Sách Tiki",
    "category_l2": "Sách tiếng Việt",
    "category_l3": "Sách Tham Khảo",
    "category_l4": "",
    "primary_category": "Sách tham khảo cấp III",
    "url": "https://tiki.vn/sach-toan-thuc-te-lop-11-p274393403.html?spid=274393404"
  },
  {
    "id": 273822776,
    "title": "Sách Nghệ thuật du ngoạn",
    "price": 131000,
    "discount": 22,
    "rating": 5.0,
    "reviews": 4,
    "quantity_sold": 100,
    "original_price": 168000,
    "category_l1": "Nhà Sách Tiki",
    "category_l2": "Sách tiếng Việt",
    "category_l3": "Sách kỹ năng sống",
    "category_l4": "",
    "primary_category": "Sách tư duy - Kỹ năng sống",
    "url": "https://tiki.vn/sach-nghe-thuat-du-ngoan-p273822776.html?spid=273822777"
  },
  {
    "id": 273691894,
    "title": "Sách Hiệu ứng cánh bướm",
    "price": 120000,
    "discount": 25,
    "rating": 4.5,
    "reviews": 13,
    "quantity_sold": 98,
    "original_price": 160000,
    "category_l1": "Nhà Sách Tiki",
    "category_l2": "Sách tiếng Việt",
    "category_l3": "Sách văn học",
    "category_l4": "Tiểu Thuyết",
    "primary_category": "Tiểu Thuyết Phương Đông",
    "url": "https://tiki.vn/sach-hieu-ung-canh-buom-p273691894.html?spid=273691895"
  },
  {
    "id": 273466782,
    "title": "Phương Pháp Cải Tâm Chuyển Vận Theo Phật Giáo - (ML)",
    "price": 206804,
    "discount": 26,
    "rating": 0.0,
    "reviews": 0,
    "quantity_sold": 14,
    "original_price": 279000,
    "category_l1": "Nhà Sách Tiki",
    "category_l2": "Sách tiếng Việt",
    "category_l3": "Sách Tôn Giáo - Tâm Linh",
    "category_l4": "",
    "primary_category": "Phật giáo",
    "url": "https://tiki.vn/phuong-phap-cai-tam-chuyen-van-theo-phat-giao-ml-p273466782.html?spid=273466783"
  },
  {
    "id": 272111582,
    "title": "Sách Người Tính Không Bằng Drama Tính",
    "price": 72000,
    "discount": 25,
    "rating": 5.0,
    "reviews": 16,
    "quantity_sold": 208,
    "original_price": 96000,
    "category_l1": "Nhà Sách Tiki",
    "category_l2": "Sách tiếng Việt",
    "category_l3": "Sách văn học",
    "category_l4": "Truyện ngắn - Tản văn - Tạp Văn",
    "primary_category": "Truyện ngắn - Tản văn - Tạp Văn Việt Nam",
    "url": "https://tiki.vn/sach-nguoi-tinh-khong-bang-drama-tinh-p272111582.html?spid=272111584"
  },
  {
    "id": 272000440,
    "title": "Sách Não Bộ Cũng Cần \"Detox\"",
    "price": 67581,
    "discount": 38,
    "rating": 5.0,
    "reviews": 1,
    "quantity_sold": 74,
    "original_price": 109000,
    "category_l1": "Nhà Sách Tiki",
    "category_l2": "Sách tiếng Việt",
    "category_l3": "Sách kỹ năng sống",
    "category_l4": "",
    "primary_category": "Sách tư duy - Kỹ năng sống",
    "url": "https://tiki.vn/sach-nao-bo-cung-can-detox-p272000440.html?spid=272000441"
  },
  {
    "id": 271270190,
    "title": "Sách Bảy quy luật tinh thần của thành công",
    "price": 47600,
    "discount": 30,
    "rating": 5.0,
    "reviews": 3,
    "quantity_sold": 81,
    "original_price": 68000,
    "category_l1": "Nhà Sách Tiki",
    "category_l2": "Sách tiếng Việt",
    "category_l3": "Sách kỹ năng sống",
    "category_l4": "",
    "primary_category": "Sách tư duy - Kỹ năng sống",
    "url": "https://tiki.vn/sach-ba-y-quy-lua-t-tinh-tha-n-cu-a-tha-nh-cong-p271270190.html?spid=271270193"
  }
]